workspaces/_init_.py
workspaces/workspaces.py
blackberry_workspaces-0.0.1.dist-info/LICENSE
blackberry_workspaces-0.0.1.dist-info/METADATA
blackberry_workspaces-0.0.1.dist-info/WHEEL
blackberry_workspaces-0.0.1.dist-info/top_level.txt
blackberry_workspaces-0.0.1.dist-info/RECORD
