Metadata-Version: 2.1
Name: blackberry-workspaces
Version: 0.0.1
Summary: A package to interact with Blackberry Workspaces via their REST API
Home-page: https://github.com/patrickgagnon/blackberry-workspaces
Author: Patrick Gagnon
Author-email: UNKNOWN
License: UNKNOWN
Platform: UNKNOWN
